{
  "author": { "id": "MDQ6VXNlcjE0MzE5MDQ=", "is_bot": false, "login": "konard", "name": "Konstantin Diachenko" },
  "body": "There was no solution summary between https://github.com/link-assistant/hive-mind/pull/843#issuecomment-4274190951 and https://github.com/link-assistant/hive-mind/pull/843#issuecomment-4274242512\n\nFull log: https://gist.githubusercontent.com/konard/5bfee8ea2a03727431e2cdcbb436d306/raw/072bea1a0867eff7269d8071461335c1989c4754/solution-draft-log-pr-1776534201375.txt\n\nWe need to download all logs and data related about the issue to this repository, make sure we compile that data to `./docs/case-studies/issue-{id}` folder, and use it to do deep case study analysis (also make sure to search online for additional facts and data), in which we will reconstruct timeline/sequence of events, list of each and all requirements from the issue, find root causes of the each problem, and propose possible solutions and solution plans for each requirement (we should also check known existing components/libraries, that solve similar problem or can help in solutions).\n\nIf there is not enough data to find actual root cause, add debug output and verbose mode if not present, that will allow us to find root cause on next iteration.\n\nIf issue related to any other repository/project, where we can report issues on GitHub, please do so. Each issue must contain reproducible examples, workarounds and suggestions for fix the issue in code.",
  "createdAt": "2026-04-19T06:23:20Z",
  "labels": [{ "id": "LA_kwDOPUU0qc8AAAACGYm6iw", "name": "bug", "description": "Something isn't working", "color": "d73a4a" }],
  "number": 1647,
  "state": "OPEN",
  "title": "--auto-attach-solution-summary didn't work",
  "updatedAt": "2026-04-19T06:23:20Z",
  "url": "https://github.com/link-assistant/hive-mind/issues/1647"
}
