{"conclusion":"failure","createdAt":"2026-05-03T21:17:07Z","databaseId":25291053689,"displayTitle":"Add --auto-delete-branch-on-merge option for watch mode","event":"pull_request","headBranch":"issue-401-ab8a9e20","headSha":"0af98ba272b9e760e2f582ef2ad14928484010ab","jobs":[{"completedAt":"2026-05-03T21:17:26Z","conclusion":"success","databaseId":74142808047,"name":"detect-changes","startedAt":"2026-05-03T21:17:15Z","status":"completed","steps":[{"completedAt":"2026-05-03T21:17:17Z","conclusion":"success","name":"Set up job","number":1,"startedAt":"2026-05-03T21:17:16Z","status":"completed"},{"completedAt":"2026-05-03T21:17:24Z","conclusion":"success","name":"Run actions/checkout@v5","number":2,"startedAt":"2026-05-03T21:17:17Z","status":"completed"},{"completedAt":"2026-05-03T21:17:25Z","conclusion":"success","name":"Detect changes","number":3,"startedAt":"2026-05-03T21:17:24Z","status":"completed"},{"completedAt":"2026-05-03T21:17:25Z","conclusion":"success","name":"Post Run actions/checkout@v5","number":6,"startedAt":"2026-05-03T21:17:25Z","status":"completed"},{"completedAt":"2026-05-03T21:17:25Z","conclusion":"success","name":"Complete job","number":7,"startedAt":"2026-05-03T21:17:25Z","status":"completed"}],"url":"https://github.com/link-assistant/hive-mind/actions/runs/25291053689/job/74142808047"},{"completedAt":"2026-05-03T21:17:07Z","conclusion":"skipped","databaseId":74142808148,"name":"Instant Release","startedAt":"2026-05-03T21:17:08Z","status":"completed","steps":[],"url":"https://github.com/link-assistant/hive-mind/actions/runs/25291053689/job/74142808148"},{"completedAt":"2026-05-03T21:17:08Z","conclusion":"skipped","databaseId":74142808181,"name":"Docker Publish Instant (${{ matrix.platform }})","startedAt":"2026-05-03T21:17:08Z","status":"completed","steps":[],"url":"https://github.com/link-assistant/hive-mind/actions/runs/25291053689/job/74142808181"},{"completedAt":"2026-05-03T21:17:07Z","conclusion":"skipped","databaseId":74142808193,"name":"Create Changeset PR","startedAt":"2026-05-03T21:17:08Z","status":"completed","steps":[],"url":"https://github.com/link-assistant/hive-mind/actions/runs/25291053689/job/74142808193"},{"completedAt":"2026-05-03T21:17:08Z","conclusion":"skipped","databaseId":74142808264,"name":"Docker Publish Instant (Merge)","startedAt":"2026-05-03T21:17:08Z","status":"completed","steps":[],"url":"https://github.com/link-assistant/hive-mind/actions/runs/25291053689/job/74142808264"},{"completedAt":"2026-05-03T21:17:08Z","conclusion":"skipped","databaseId":74142808265,"name":"Docker Publish DinD Instant (${{ matrix.platform }})","startedAt":"2026-05-03T21:17:08Z","status":"completed","steps":[],"url":"https://github.com/link-assistant/hive-mind/actions/runs/25291053689/job/74142808265"},{"completedAt":"2026-05-03T21:17:08Z","conclusion":"skipped","databaseId":74142808309,"name":"Docker Publish DinD Instant (Merge)","startedAt":"2026-05-03T21:17:08Z","status":"completed","steps":[],"url":"https://github.com/link-assistant/hive-mind/actions/runs/25291053689/job/74142808309"},{"completedAt":"2026-05-03T21:17:08Z","conclusion":"skipped","databaseId":74142808543,"name":"Helm Release (Instant)","startedAt":"2026-05-03T21:17:08Z","status":"completed","steps":[],"url":"https://github.com/link-assistant/hive-mind/actions/runs/25291053689/job/74142808543"},{"completedAt":"2026-05-03T21:18:30Z","conclusion":"success","databaseId":74142826099,"name":"lint","startedAt":"2026-05-03T21:17:28Z","status":"completed","steps":[{"completedAt":"2026-05-03T21:17:30Z","conclusion":"success","name":"Set up job","number":1,"startedAt":"2026-05-03T21:17:29Z","status":"completed"},{"completedAt":"2026-05-03T21:17:37Z","conclusion":"success","name":"Checkout repository","number":2,"startedAt":"2026-05-03T21:17:30Z","status":"completed"},{"completedAt":"2026-05-03T21:17:38Z","conclusion":"success","name":"Simulate fresh merge with base branch (PR only)","number":3,"startedAt":"2026-05-03T21:17:37Z","status":"completed"},{"completedAt":"2026-05-03T21:17:41Z","conclusion":"success","name":"Setup Node.js","number":4,"startedAt":"2026-05-03T21:17:38Z","status":"completed"},{"completedAt":"2026-05-03T21:17:49Z","conclusion":"success","name":"Install dependencies","number":5,"startedAt":"2026-05-03T21:17:41Z","status":"completed"},{"completedAt":"2026-05-03T21:18:13Z","conclusion":"success","name":"Run Prettier format check","number":6,"startedAt":"2026-05-03T21:17:49Z","status":"completed"},{"completedAt":"2026-05-03T21:18:19Z","conclusion":"success","name":"Run ESLint","number":7,"startedAt":"2026-05-03T21:18:13Z","status":"completed"},{"completedAt":"2026-05-03T21:18:29Z","conclusion":"success","name":"Run code duplication check","number":8,"startedAt":"2026-05-03T21:18:19Z","status":"completed"},{"completedAt":"2026-05-03T21:18:29Z","conclusion":"success","name":"Post Setup Node.js","number":15,"startedAt":"2026-05-03T21:18:29Z","status":"completed"},{"completedAt":"2026-05-03T21:18:29Z","conclusion":"success","name":"Post Checkout repository","number":16,"startedAt":"2026-05-03T21:18:29Z","status":"completed"},{"completedAt":"2026-05-03T21:18:29Z","conclusion":"success","name":"Complete job","number":17,"startedAt":"2026-05-03T21:18:29Z","status":"completed"}],"url":"https://github.com/link-assistant/hive-mind/actions/runs/25291053689/job/74142826099"},{"completedAt":"2026-05-03T21:17:41Z","conclusion":"success","databaseId":74142826105,"name":"Check for Manual Version Changes","startedAt":"2026-05-03T21:17:29Z","status":"completed","steps":[{"completedAt":"2026-05-03T21:17:30Z","conclusion":"success","name":"Set up job","number":1,"startedAt":"2026-05-03T21:17:30Z","status":"completed"},{"completedAt":"2026-05-03T21:17:39Z","conclusion":"success","name":"Run actions/checkout@v5","number":2,"startedAt":"2026-05-03T21:17:30Z","status":"completed"},{"completedAt":"2026-05-03T21:17:39Z","conclusion":"success","name":"Check for version changes in package.json","number":3,"startedAt":"2026-05-03T21:17:39Z","status":"completed"},{"completedAt":"2026-05-03T21:17:39Z","conclusion":"success","name":"Post Run actions/checkout@v5","number":6,"startedAt":"2026-05-03T21:17:39Z","status":"completed"},{"completedAt":"2026-05-03T21:17:39Z","conclusion":"success","name":"Complete job","number":7,"startedAt":"2026-05-03T21:17:39Z","status":"completed"}],"url":"https://github.com/link-assistant/hive-mind/actions/runs/25291053689/job/74142826105"},{"completedAt":"2026-05-03T21:17:51Z","conclusion":"failure","databaseId":74142826110,"name":"Check for Changesets","startedAt":"2026-05-03T21:17:28Z","status":"completed","steps":[{"completedAt":"2026-05-03T21:17:30Z","conclusion":"success","name":"Set up job","number":1,"startedAt":"2026-05-03T21:17:29Z","status":"completed"},{"completedAt":"2026-05-03T21:17:38Z","conclusion":"success","name":"Run actions/checkout@v5","number":2,"startedAt":"2026-05-03T21:17:30Z","status":"completed"},{"completedAt":"2026-05-03T21:17:41Z","conclusion":"success","name":"Setup Node.js","number":3,"startedAt":"2026-05-03T21:17:38Z","status":"completed"},{"completedAt":"2026-05-03T21:17:49Z","conclusion":"success","name":"Install dependencies","number":4,"startedAt":"2026-05-03T21:17:41Z","status":"completed"},{"completedAt":"2026-05-03T21:17:49Z","conclusion":"failure","name":"Check for changesets","number":5,"startedAt":"2026-05-03T21:17:49Z","status":"completed"},{"completedAt":"2026-05-03T21:17:49Z","conclusion":"skipped","name":"Post Setup Node.js","number":9,"startedAt":"2026-05-03T21:17:49Z","status":"completed"},{"completedAt":"2026-05-03T21:17:49Z","conclusion":"success","name":"Post Run actions/checkout@v5","number":10,"startedAt":"2026-05-03T21:17:49Z","status":"completed"},{"completedAt":"2026-05-03T21:17:49Z","conclusion":"success","name":"Complete job","number":11,"startedAt":"2026-05-03T21:17:49Z","status":"completed"}],"url":"https://github.com/link-assistant/hive-mind/actions/runs/25291053689/job/74142826110"},{"completedAt":"2026-05-03T21:17:51Z","conclusion":"skipped","databaseId":74142849186,"name":"test-compilation","startedAt":"2026-05-03T21:17:51Z","status":"completed","steps":[],"url":"https://github.com/link-assistant/hive-mind/actions/runs/25291053689/job/74142849186"},{"completedAt":"2026-05-03T21:17:51Z","conclusion":"skipped","databaseId":74142849282,"name":"check-file-line-limits","startedAt":"2026-05-03T21:17:51Z","status":"completed","steps":[],"url":"https://github.com/link-assistant/hive-mind/actions/runs/25291053689/job/74142849282"},{"completedAt":"2026-05-03T21:17:51Z","conclusion":"skipped","databaseId":74142849284,"name":"validate-docs","startedAt":"2026-05-03T21:17:51Z","status":"completed","steps":[],"url":"https://github.com/link-assistant/hive-mind/actions/runs/25291053689/job/74142849284"},{"completedAt":"2026-05-03T21:17:51Z","conclusion":"skipped","databaseId":74142849285,"name":"helm-pr-check","startedAt":"2026-05-03T21:17:51Z","status":"completed","steps":[],"url":"https://github.com/link-assistant/hive-mind/actions/runs/25291053689/job/74142849285"},{"completedAt":"2026-05-03T21:18:30Z","conclusion":"skipped","databaseId":74142887335,"name":"test-suites","startedAt":"2026-05-03T21:18:30Z","status":"completed","steps":[],"url":"https://github.com/link-assistant/hive-mind/actions/runs/25291053689/job/74142887335"},{"completedAt":"2026-05-03T21:18:30Z","conclusion":"skipped","databaseId":74142887336,"name":"docker-pr-check","startedAt":"2026-05-03T21:18:30Z","status":"completed","steps":[],"url":"https://github.com/link-assistant/hive-mind/actions/runs/25291053689/job/74142887336"},{"completedAt":"2026-05-03T21:18:30Z","conclusion":"skipped","databaseId":74142887450,"name":"Release","startedAt":"2026-05-03T21:18:30Z","status":"completed","steps":[],"url":"https://github.com/link-assistant/hive-mind/actions/runs/25291053689/job/74142887450"},{"completedAt":"2026-05-03T21:18:30Z","conclusion":"skipped","databaseId":74142887465,"name":"test-execution","startedAt":"2026-05-03T21:18:30Z","status":"completed","steps":[],"url":"https://github.com/link-assistant/hive-mind/actions/runs/25291053689/job/74142887465"},{"completedAt":"2026-05-03T21:18:30Z","conclusion":"skipped","databaseId":74142887473,"name":"memory-check-linux","startedAt":"2026-05-03T21:18:30Z","status":"completed","steps":[],"url":"https://github.com/link-assistant/hive-mind/actions/runs/25291053689/job/74142887473"},{"completedAt":"2026-05-03T21:18:30Z","conclusion":"skipped","databaseId":74142887549,"name":"Docker Publish (${{ matrix.platform }})","startedAt":"2026-05-03T21:18:30Z","status":"completed","steps":[],"url":"https://github.com/link-assistant/hive-mind/actions/runs/25291053689/job/74142887549"},{"completedAt":"2026-05-03T21:18:30Z","conclusion":"skipped","databaseId":74142887580,"name":"Docker Publish DinD (${{ matrix.platform }})","startedAt":"2026-05-03T21:18:30Z","status":"completed","steps":[],"url":"https://github.com/link-assistant/hive-mind/actions/runs/25291053689/job/74142887580"},{"completedAt":"2026-05-03T21:18:30Z","conclusion":"skipped","databaseId":74142887675,"name":"Helm Release","startedAt":"2026-05-03T21:18:31Z","status":"completed","steps":[],"url":"https://github.com/link-assistant/hive-mind/actions/runs/25291053689/job/74142887675"},{"completedAt":"2026-05-03T21:18:30Z","conclusion":"skipped","databaseId":74142887710,"name":"Docker Publish DinD (Merge)","startedAt":"2026-05-03T21:18:31Z","status":"completed","steps":[],"url":"https://github.com/link-assistant/hive-mind/actions/runs/25291053689/job/74142887710"},{"completedAt":"2026-05-03T21:18:30Z","conclusion":"skipped","databaseId":74142887719,"name":"Docker Publish (Merge)","startedAt":"2026-05-03T21:18:31Z","status":"completed","steps":[],"url":"https://github.com/link-assistant/hive-mind/actions/runs/25291053689/job/74142887719"}],"name":"Checks and release","status":"completed","updatedAt":"2026-05-03T21:18:31Z","url":"https://github.com/link-assistant/hive-mind/actions/runs/25291053689","workflowName":"Checks and release"}
